[
    {
        "version": "0.2.12",
        "releaseDate": "2018-04-07 09:21:05",
        "releaseTimestamp": "1523092865",
        "hash": "f922ff9379cd8f9d66a225269024b3fd9ab17f40",
        "commits": [
            "[2018-04-07] Bumped version to 0.2.12",
            "[2018-04-07]\tMinor bugfix in composer.json template"
        ]
    },
    {
        "version": "0.2.11",
        "releaseDate": "2018-04-04 12:37:43",
        "releaseTimestamp": "1522845463",
        "hash": "07434bf0ed04d9df41994656e3eb069f5330c982",
        "commits": [
            "[2018-04-04] Bumped version to 0.2.11"
        ]
    },
    {
        "version": "0.2.10",
        "releaseDate": "2018-04-04 12:31:34",
        "releaseTimestamp": "1522845094",
        "hash": "0189671818b152060f5762ee38373888b0542218",
        "commits": [
            "[2018-04-04] Bumped version to 0.2.10"
        ]
    },
    {
        "version": "0.2.9",
        "releaseDate": "2018-04-04 12:31:04",
        "releaseTimestamp": "1522845064",
        "hash": "6ad81397bdce8eb83da3fe2990eb3428ad765a52",
        "commits": [
            "[2018-04-04] Bumped version to 0.2.9",
            "[2018-04-04]\tMerge branch 'feature\/cscart-4-1'",
            "[2018-04-04]\tBackward compatibility with CS-Cart 4.1.x"
        ]
    }
]